setup.py
aspgen/__init__.py
aspgen.egg-info/PKG-INFO
aspgen.egg-info/SOURCES.txt
aspgen.egg-info/dependency_links.txt
aspgen.egg-info/entry_points.txt
aspgen.egg-info/not-zip-safe
aspgen.egg-info/top_level.txt