Metadata-Version: 1.1
Name: aspgen
Version: 0.0.0
Summary: A Secure Password GENerator
Home-page: https://github.com/TheOneHyer/aspgen
Author: Alex Hyer
Author-email: theonehyer@gmail.com
License: GPLv3
Download-URL: https://github.com/TheOneHyer/aspgen/tarball/0.0.0
Keywords: secure password generator
Platform: UNKNOWN
Classifier: Development Status :: 1 - Planning
Classifier: Intended Audience :: End Users/Desktop
Classifier: License :: OSI Approved :: GNU General Public License v3 (GPLv3)
Classifier: Natural Language :: English
Classifier: Operating System :: OS Independent
Classifier: Programming Language :: Python :: 2.7
Classifier: Programming Language :: Python :: 3.4
Classifier: Topic :: Security
